mopidy_tidal/__init__.py
mopidy_tidal/auth_http_server.py
mopidy_tidal/backend.py
mopidy_tidal/display.py
mopidy_tidal/ext.conf
mopidy_tidal/full_models_mappers.py
mopidy_tidal/library.py
mopidy_tidal/lru_cache.py
mopidy_tidal/playback.py
mopidy_tidal/playlists.py
mopidy_tidal/ref_models_mappers.py
mopidy_tidal/search.py
mopidy_tidal/utils.py
Mopidy_TidalOAuth-0.3.2.dist-info/LICENSE
Mopidy_TidalOAuth-0.3.2.dist-info/METADATA
Mopidy_TidalOAuth-0.3.2.dist-info/WHEEL
Mopidy_TidalOAuth-0.3.2.dist-info/entry_points.txt
Mopidy_TidalOAuth-0.3.2.dist-info/top_level.txt
Mopidy_TidalOAuth-0.3.2.dist-info/RECORD
