Metadata-Version: 2.1
Name: Mopidy-TidalOAuth
Version: 0.3.2
Summary: Tidal music service integration
Home-page: https://github.com/quodrum-glas/mopidy-tidal
Author: Simone Fantini
Author-email: mones88@gmail.com
Maintainer: quodrumglas
Maintainer-email: quodrumglas@email.com
License: Apache License, Version 2.0
Platform: UNKNOWN
Classifier: Environment :: No Input/Output (Daemon)
Classifier: Intended Audience :: End Users/Desktop
Classifier: License :: OSI Approved :: Apache Software License
Classifier: Operating System :: OS Independent
Classifier: Programming Language :: Python :: 2
Classifier: Programming Language :: Python :: 3
Classifier: Topic :: Multimedia :: Sound/Audio :: Players
Requires-Dist: setuptools
Requires-Dist: Mopidy (>=1.0)
Requires-Dist: Pykka (>=1.1)
Requires-Dist: tidaloauth4mopidy (==0.2.0)
Requires-Dist: requests (>=2.0.0)
